{
  "swagger": "2.0",
  "info": {
    "title": "\u8d22\u7a0e\u4e91;\u51ed\u8bc1;",
    "version": "version not set"
  },
  "tags": [
    {
      "name": "Voucher"
    }
  ],
  "consumes": [
    "application/json"
  ],
  "produces": [
    "application/json"
  ],
  "paths": {
    "/openapi/v2/fi/voucher": {
      "get": {
        "summary": "\u51ed\u8bc1\u5217\u8868;\u83b7\u53d6\u51ed\u8bc1\u5217\u8868;1.0.11",
        "operationId": "Voucher_list",
        "responses": {
          "200": {
            "description": "A successful response.",
            "schema": {
              "$ref": "#/definitions/VoucherListReply"
            }
          },
          "default": {
            "description": "An unexpected error response.",
            "schema": {
              "$ref": "#/definitions/Status"
            }
          }
        },
        "parameters": [
          {
            "name": "search",
            "description": "a=\u6a21\u7cca\u641c\u7d22\uff0c\u5907\u6ce8;b=30;c=\u51ed\u8bc1;d=false.",
            "in": "query",
            "required": false,
            "type": "string"
          },
          {
            "name": "explanation",
            "description": "a=\u6a21\u7cca\u641c\u7d22\uff0c\u6458\u8981;b=30;c=\u6458\u8981;d=false.",
            "in": "query",
            "required": false,
            "type": "string"
          },
          {
            "name": "start_period",
            "description": "a=\u8d77\u59cb\u671f\u95f4;b=6;c=202206;d=false.",
            "in": "query",
            "required": false,
            "type": "string"
          },
          {
            "name": "end_period",
            "description": "a=\u7ed3\u675f\u671f\u95f4;b=6;c=202206;d=false.",
            "in": "query",
            "required": false,
            "type": "string"
          },
          {
            "name": "account_ids",
            "description": "a=\u79d1\u76eeid\u6570\u7ec4;b=30;c=[];d=false.",
            "in": "query",
            "required": false,
            "type": "array",
            "items": {
              "type": "string"
            },
            "collectionFormat": "multi"
          },
          {
            "name": "bill_status",
            "description": "a=\u5355\u636e\u72b6\u6001\uff08\u6240\u6709\uff1a\u201c\u201d\uff0c\u5df2\u5ba1\u6838\uff1a\u201cC\u201d\uff0c\u672a\u5ba1\u6838\uff1a\u201cA\u201d\uff09;b=1;c=C;d=false.",
            "in": "query",
            "required": false,
            "type": "string"
          },
          {
            "name": "number",
            "description": "a=\u51ed\u8bc1\u53f7;b=30;c=1;d=false.",
            "in": "query",
            "required": false,
            "type": "string"
          },
          {
            "name": "create_start_time",
            "description": "a=\u521b\u5efa\u65f6\u95f4-\u5f00\u59cb\u65f6\u95f4\u7684\u65f6\u95f4\u6233(\u6beb\u79d2);b=13;c=1234567890123;d=false.",
            "in": "query",
            "required": false,
            "type": "string"
          },
          {
            "name": "create_end_time",
            "description": "a=\u521b\u5efa\u65f6\u95f4-\u7ed3\u675f\u65f6\u95f4\u7684\u65f6\u95f4\u6233(\u6beb\u79d2);b=13;c=1234567890123;d=false.",
            "in": "query",
            "required": false,
            "type": "string"
          },
          {
            "name": "modify_start_time",
            "description": "a=\u4fee\u6539\u65f6\u95f4-\u5f00\u59cb\u65f6\u95f4\u7684\u65f6\u95f4\u6233(\u6beb\u79d2);b=13;c=1234567890123;d=false.",
            "in": "query",
            "required": false,
            "type": "string"
          },
          {
            "name": "modify_end_time",
            "description": "a=\u4fee\u6539\u65f6\u95f4-\u7ed3\u675f\u65f6\u95f4\u7684\u65f6\u95f4\u6233(\u6beb\u79d2);b=13;c=1234567890123;d=false.",
            "in": "query",
            "required": false,
            "type": "string"
          },
          {
            "name": "page",
            "description": "a=\u5f53\u524d\u9875\uff0c\u9ed8\u8ba41;b=1000;c=1;d=false.",
            "in": "query",
            "required": false,
            "type": "string"
          },
          {
            "name": "page_size",
            "description": "a=\u6bcf\u9875\u663e\u793a\u6761\u6570\u9ed8\u8ba410;b=100;c=100;d=false.",
            "in": "query",
            "required": false,
            "type": "string"
          },
          {
            "name": "source_bill_no",
            "description": "a=\u5916\u90e8\u552f\u4e00\u6807\u8bc6;b=30;c=001;d=false.",
            "in": "query",
            "required": false,
            "type": "string"
          }
        ],
        "tags": [
          "Voucher"
        ]
      },
      "post": {
        "summary": "\u51ed\u8bc1\u4fdd\u5b58;\u51ed\u8bc1\u65b0\u589e\u53ca\u4fee\u6539\u3002\u5ba1\u6838\u3001\u5220\u9664\u7b49\u8be6\u89c1[\u901a\u7528\u64cd\u4f5c\u63a5\u53e3](https://open.jdy.com/#/files/api/detail?index=2&categrayId=3cc8ee9a663e11eda5c84b5d383a2b93&id=9e804b8c712511eda0b39f724d124b07);1.0.23",
        "operationId": "Voucher_save",
        "responses": {
          "200": {
            "description": "A successful response.",
            "schema": {
              "$ref": "#/definitions/PubReply"
            }
          },
          "default": {
            "description": "An unexpected error response.",
            "schema": {
              "$ref": "#/definitions/Status"
            }
          }
        },
        "parameters": [
          {
            "name": "body",
            "in": "body",
            "required": true,
            "schema": {
              "$ref": "#/definitions/VoucherSaveRequest"
            }
          }
        ],
        "tags": [
          "Voucher"
        ]
      }
    },
    "/openapi/v2/fi/voucher_detail": {
      "get": {
        "summary": "\u51ed\u8bc1\u8be6\u60c5;\u83b7\u53d6\u51ed\u8bc1\u8be6\u60c5;1.0.11",
        "operationId": "Voucher_detail",
        "responses": {
          "200": {
            "description": "A successful response.",
            "schema": {
              "$ref": "#/definitions/VoucherDetailReply"
            }
          },
          "default": {
            "description": "An unexpected error response.",
            "schema": {
              "$ref": "#/definitions/Status"
            }
          }
        },
        "parameters": [
          {
            "name": "id",
            "description": "a=\uff08id\u548cnumber\u4e8c\u9009\u4e00\uff09;b=2147483647;c=1;d=false.",
            "in": "query",
            "required": false,
            "type": "string"
          },
          {
            "name": "number",
            "description": "a=\u7f16\u7801\uff08id\u4e0enumber\u4e8c\u9009\u4e00\uff09;b=30;c=001;d=false.",
            "in": "query",
            "required": false,
            "type": "string"
          }
        ],
        "tags": [
          "Voucher"
        ]
      }
    }
  },
  "definitions": {
    "Any": {
      "type": "object",
      "properties": {
        "@type": {
          "type": "string",
          "description": "A URL/resource name that uniquely identifies the type of the serialized\nprotocol buffer message. This string must contain at least\none \"/\" character. The last segment of the URL's path must represent\nthe fully qualified name of the type (as in\n`path/google.protobuf.Duration`). The name should be in a canonical form\n(e.g., leading \".\" is not accepted).\n\nIn practice, teams usually precompile into the binary all types that they\nexpect it to use in the context of Any. However, for URLs which use the\nscheme `http`, `https`, or no scheme, one can optionally set up a type\nserver that maps type URLs to message definitions as follows:\n\n* If no scheme is provided, `https` is assumed.\n* An HTTP GET on the URL must yield a [google.protobuf.Type][]\n  value in binary format, or produce an error.\n* Applications are allowed to cache lookup results based on the\n  URL, or have them precompiled into a binary to avoid any\n  lookup. Therefore, binary compatibility needs to be preserved\n  on changes to types. (Use versioned type names to manage\n  breaking changes.)\n\nNote: this functionality is not currently available in the official\nprotobuf release, and it is not used for type URLs beginning with\ntype.googleapis.com.\n\nSchemes other than `http`, `https` (or the empty scheme) might be\nused with implementation specific semantics."
        }
      },
      "additionalProperties": {},
      "description": "`Any` contains an arbitrary serialized protocol buffer message along with a\nURL that describes the type of the serialized message.\n\nProtobuf library provides support to pack/unpack Any values in the form\nof utility functions or additional generated methods of the Any type.\n\nExample 1: Pack and unpack a message in C++.\n\n    Foo foo = ...;\n    Any any;\n    any.PackFrom(foo);\n    ...\n    if (any.UnpackTo(&foo)) {\n      ...\n    }\n\nExample 2: Pack and unpack a message in Java.\n\n    Foo foo = ...;\n    Any any = Any.pack(foo);\n    ...\n    if (any.is(Foo.class)) {\n      foo = any.unpack(Foo.class);\n    }\n\n Example 3: Pack and unpack a message in Python.\n\n    foo = Foo(...)\n    any = Any()\n    any.Pack(foo)\n    ...\n    if any.Is(Foo.DESCRIPTOR):\n      any.Unpack(foo)\n      ...\n\n Example 4: Pack and unpack a message in Go\n\n     foo := &pb.Foo{...}\n     any, err := ptypes.MarshalAny(foo)\n     ...\n     foo := &pb.Foo{}\n     if err := ptypes.UnmarshalAny(any, foo); err != nil {\n       ...\n     }\n\nThe pack methods provided by protobuf library will by default use\n'type.googleapis.com/full.type.name' as the type URL and the unpack\nmethods only use the fully qualified type name after the last '/'\nin the type URL, for example \"foo.bar.com/x/y.z\" will yield type\nname \"y.z\".\n\n\nJSON\n====\nThe JSON representation of an `Any` value uses the regular\nrepresentation of the deserialized, embedded message, with an\nadditional field `@type` which contains the type URL. Example:\n\n    package google.profile;\n    message Person {\n      string first_name = 1;\n      string last_name = 2;\n    }\n\n    {\n      \"@type\": \"type.googleapis.com/google.profile.Person\",\n      \"firstName\": <string>,\n      \"lastName\": <string>\n    }\n\nIf the embedded message type is well-known and has a custom JSON\nrepresentation, that representation will be embedded adding a field\n`value` which holds the custom JSON in addition to the `@type`\nfield. Example (for message [google.protobuf.Duration][]):\n\n    {\n      \"@type\": \"type.googleapis.com/google.protobuf.Duration\",\n      \"value\": \"1.212s\"\n    }"
    },
    "Entry.Assist": {
      "type": "object",
      "properties": {
        "id": {
          "type": "string",
          "title": "a=\u8f85\u52a9\u6838\u7b97id;b=2147483647;c=1;d=true"
        },
        "number": {
          "type": "string",
          "title": "a=\u8f85\u52a9\u6838\u7b97\u7f16\u7801;b=30;c=001;d=false"
        },
        "type": {
          "type": "string",
          "title": "a=\u6838\u7b97\u9879\u76ee\u7c7b\u522b(bd_customer:\u5ba2\u6237\uff0cbd_supplier:\u4f9b\u5e94\u5546\uff0c bd_material:\u5546\u54c1\uff0cbd_department:\u90e8\u95e8\uff0c bd_auxinfo:\u8f85\u52a9\u8d44\u6599\uff0cbd_employee:\u804c\u5458\uff0cbd_store:\u4ed3\u5e93);b=20;c=bd_auxinfo;d=true"
        },
        "bd_aux_info_type_id": {
          "type": "string",
          "title": "a=\u5f53type\u4e3abd_auxinfo\u65f6,\u8f85\u52a9\u8d44\u6599\u7c7b\u522bid;b=2147483647;c=1;d=false"
        },
        "bd_aux_info_type_number": {
          "type": "string",
          "title": "a=\u5f53type\u4e3abd_auxinfo\u65f6,\u8f85\u52a9\u8d44\u6599\u7c7b\u522b\u7f16\u7801,\u540c\u65f6\u4f20id\u65f6\u4f18\u5148\u53d6id;b=30;c=001;d=false"
        }
      }
    },
    "Item.Entry": {
      "type": "object",
      "properties": {
        "id": {
          "type": "string",
          "title": "a=\u5206\u5f55ID;b=2147483647;c=1;d=true"
        },
        "explanation": {
          "type": "string",
          "title": "a=\u6458\u8981;b=100;c=\u65e0;d=true"
        },
        "account_id": {
          "type": "string",
          "title": "a=\u79d1\u76ee id;b=2147483647;c=1;d=true"
        },
        "account_number": {
          "type": "string",
          "title": "a=\u4f20\u5165account_number\u65f6\uff0caccount_id\u975e\u5fc5\u586b;b=30;c=001;d=true"
        },
        "currency_id": {
          "type": "string",
          "title": "a=\u5e01\u522bid;b=2147483647;c=1;d=true"
        },
        "debit_amount": {
          "type": "string",
          "title": "a=\u501f\u65b9\u91d1\u989d(\u672c\u4f4d\u5e01)\uff08dc=1\u65f6\u5fc5\u586b\uff0cdc=-1\u65f6\u4e0d\u586b\uff09;b=999999999;c=100;d=true"
        },
        "credit_amount": {
          "type": "string",
          "title": "a=\u8d37\u65b9\u91d1\u989d(\u672c\u4f4d\u5e01)\uff08dc=-1\u65f6\u5fc5\u586b\uff0cdc=1\u65f6\u4e0d\u586b\uff09;b=999999999;c=100;d=true"
        },
        "amount_for": {
          "type": "string",
          "title": "a=\u91d1\u989d\uff08\u539f\u5e01\uff09;b=999999999;c=100;d=true"
        },
        "dc": {
          "type": "string",
          "title": "a=\u501f\u8d37\u65b9\u5411\uff081\uff1a\u501f\uff0c-1\uff1a\u8d37\uff09;b=1;c=1;d=true"
        },
        "quantity": {
          "type": "number",
          "format": "double",
          "title": "a=\u6570\u91cf;c=1;d=false"
        },
        "assist_list": {
          "type": "array",
          "items": {
            "$ref": "#/definitions/Entry.Assist"
          },
          "title": "a=\u8f85\u52a9\u6838\u7b97;b=8;c=[];d=false"
        },
        "price": {
          "type": "string",
          "title": "a=\u4ef7\u683c;b=99;c=100;d=false"
        }
      }
    },
    "PubReply": {
      "type": "object",
      "properties": {
        "ids": {
          "type": "array",
          "items": {
            "type": "string"
          },
          "title": "a=\u5355\u636eid\u6570\u7ec4\u5bf9\u8c61;c=[\"1\"];d=true"
        },
        "errors": {
          "type": "array",
          "items": {
            "type": "string"
          },
          "title": "a=\u5931\u8d25\u4fe1\u606f\u6570\u7ec4;c=[\"\u5931\u8d25\"];d=true"
        }
      },
      "title": "\u4fdd\u5b58\u8fd4\u56deid\u6570\u7ec4\u5bf9\u8c61"
    },
    "Row.SourceBill": {
      "type": "object",
      "properties": {
        "src_bill_id": {
          "type": "string",
          "title": "a=\u4e1a\u52a1\u5355\u636eid;b=999999999;c=111;"
        },
        "src_bill_type": {
          "type": "string",
          "title": "a=\u4e1a\u52a1\u5355\u636e\u7c7b\u578b\u8be6\u89c1[\u57fa\u7840\u8d44\u6599\u53ca\u5355\u636e\u7c7b\u578b](https://open.jdy.com/#/files/api/detail?index=3&categrayId=3cc8ee9a663e11eda5c84b5d383a2b93&id=dd7ee492712611eda0b375f5553347df);c=sal_order_bill"
        },
        "src_bill_no": {
          "type": "string",
          "title": "a=\u4e1a\u52a1\u5355\u636enumber;b=999999999;c=BM001;d=true"
        }
      }
    },
    "Status": {
      "type": "object",
      "properties": {
        "code": {
          "type": "integer",
          "format": "int32"
        },
        "message": {
          "type": "string"
        },
        "details": {
          "type": "array",
          "items": {
            "$ref": "#/definitions/Any"
          }
        }
      }
    },
    "VoucherDetailReply": {
      "type": "object",
      "properties": {
        "id": {
          "type": "string",
          "title": "a=\u51ed\u8bc1id;b=2147483647;c=1;d=true"
        },
        "date": {
          "type": "string",
          "title": "a=\u51ed\u8bc1\u65e5\u671f;b=10;c=2022-06-09;d=true"
        },
        "period": {
          "type": "string",
          "title": "a=\u51ed\u8bc1\u671f\u95f4;b=6;c=202206;d=true"
        },
        "number": {
          "type": "string",
          "title": "a=\u51ed\u8bc1\u53f7;b=100;c=1;d=true"
        },
        "voucher_no": {
          "type": "string",
          "title": "a=\u51ed\u8bc1\u5b57\u53f7;b=1;c=\u8bb0;d=true"
        },
        "bill_status": {
          "type": "string",
          "title": "a=\u72b6\u6001,\u6682\u5b58\uff1a\u201cA\u201d\uff0c\u4fdd\u5b58\uff1a\u201cB\u201d\uff0c\u5df2\u5ba1\u6838\uff1a\u201cC\u201d\uff0c\u5df2\u4f5c\u5e9f\uff1a\u201cD\u201d;b=1;c=A;d=true"
        },
        "group_id": {
          "type": "string",
          "title": "a=\u51ed\u8bc1\u5b57id;b=2147483647;c=1;d=true"
        },
        "group_number": {
          "type": "string",
          "title": "a=\u51ed\u8bc1\u5b57\u7f16\u7801;b=30;c=001;d=true"
        },
        "group_name": {
          "type": "string",
          "title": "a=\u51ed\u8bc1\u5b57\u540d\u79f0;b=30;c=\u8bb0;d=true"
        },
        "debit_total": {
          "type": "string",
          "title": "a=\u501f\u65b9\u603b\u91d1\u989d;b=2^128;c=100;d=true"
        },
        "credit_total": {
          "type": "string",
          "title": "a=\u8d37\u65b9\u603b\u91d1\u989d;b=2^128;c=100;d=true"
        },
        "source_bill_type": {
          "type": "string",
          "title": "\u8fc7\u65f6\u5b57\u6bb5\uff0c\u4e0d\u751f\u6210\u5bf9\u5916API\u6587\u6863:\u6a21\u7cca\u641c\u7d22"
        },
        "source_bill_id": {
          "type": "string",
          "title": "\u8fc7\u65f6\u5b57\u6bb5\uff0c\u4e0d\u751f\u6210\u5bf9\u5916API\u6587\u6863:\u6a21\u7cca\u641c\u7d22"
        },
        "have_reverse": {
          "type": "boolean",
          "title": "a=\u662f\u5426\u5df2\u88ab\u51b2\u9500;b=5;c=true;d=true"
        },
        "is_reverse": {
          "type": "boolean",
          "title": "a=\u662f\u5426\u51b2\u9500\u51ed\u8bc1;b=5;c=true;d=true"
        },
        "entry_list": {
          "type": "array",
          "items": {
            "$ref": "#/definitions/VoucherDetailReply.Entry"
          },
          "title": "a=\u51ed\u8bc1\u5206\u5f55;b=8;c=[];d=false"
        },
        "src_bill": {
          "type": "array",
          "items": {
            "$ref": "#/definitions/VoucherDetailReply.SourceBill"
          },
          "title": "a=\u51ed\u8bc1\u5173\u8054\u7684\u6e90\u5355\u4fe1\u606f;b=8;c=[];"
        }
      }
    },
    "VoucherDetailReply.Assist": {
      "type": "object",
      "properties": {
        "id": {
          "type": "string",
          "title": "a=\u8f85\u52a9\u6838\u7b97id\uff08id\u4e0enumber\u4e8c\u9009\u4e00\uff09;b=2147483647;c=1;d=false"
        },
        "type": {
          "type": "string",
          "title": "a=\u8f85\u52a9\u6838\u7b97\u7c7b\u522b;b=20;c=bd_auxinfo;d=true"
        },
        "bd_aux_info_type_id": {
          "type": "string",
          "title": "a=\u5f53type\u4e3abd_auxinfo\u65f6,\u8f85\u52a9\u8d44\u6599\u7c7b\u522bid;b=2147483647;c=1;d=false"
        },
        "number": {
          "type": "string",
          "title": "a=\u8f85\u52a9\u6838\u7b97number\uff08id\u4e0enumber\u4e8c\u9009\u4e00\uff09;b=30;c=001;d=false"
        }
      }
    },
    "VoucherDetailReply.Entry": {
      "type": "object",
      "properties": {
        "id": {
          "type": "string",
          "title": "a=\u5206\u5f55ID;b=2147483647;c=1;d=true"
        },
        "seq": {
          "type": "string",
          "title": "a=\u5206\u5f55\u5e8f\u53f7;b=100;c=1;d=true"
        },
        "explanation": {
          "type": "string",
          "title": "a=\u6458\u8981;b=100;c=\u65e0;d=true"
        },
        "account_id": {
          "type": "string",
          "title": "a=\u79d1\u76ee id;b=2147483647;c=1;d=true"
        },
        "account_name": {
          "type": "string",
          "title": "a=\u79d1\u76ee \u540d\u79f0;b=30;c=\u5e93\u5b58\u73b0\u91d1;d=true"
        },
        "account_number": {
          "type": "string",
          "title": "a=\u79d1\u76ee \u7f16\u7801;b=30;c=001;d=true"
        },
        "measure_unit_id": {
          "type": "string",
          "title": "a=\u5355\u4f4did;b=2147483647;c=1;d=true"
        },
        "measure_unit_name": {
          "type": "string",
          "title": "a=\u5355\u4f4d\u540d\u79f0;b=30;c=\u4e2a;d=true"
        },
        "measure_unit_number": {
          "type": "string",
          "title": "a=\u5355\u4f4d\u7f16\u7801;b=30;c=001;d=true"
        },
        "currency_id": {
          "type": "string",
          "title": "a=\u5e01\u522bid;b=2147483647;c=1;d=true"
        },
        "currency_name": {
          "type": "string",
          "title": "a=\u5e01\u522b\u540d\u79f0;b=30;c=\u5143;d=true"
        },
        "currency_number": {
          "type": "string",
          "title": "a=\u5e01\u522b\u7f16\u7801;b=30;c=001;d=true"
        },
        "debit_amount": {
          "type": "string",
          "title": "a=\u501f\u65b9\u91d1\u989d;b=999999999;c=100;d=true"
        },
        "credit_amount": {
          "type": "string",
          "title": "a=\u8d37\u65b9\u91d1\u989d;b=999999999;c=100;d=true"
        },
        "amount_for": {
          "type": "string",
          "title": "a=\u91d1\u989d\uff08\u672c\u4f4d\u5e01\uff09;b=999999999;c=100;d=true"
        },
        "price": {
          "type": "string",
          "title": "a=\u5355\u4ef7;b=999999999;c=100;d=true"
        },
        "quantity": {
          "type": "string",
          "title": "a=\u6570\u91cf;b=999999;c=1;d=true"
        },
        "dc": {
          "type": "string",
          "title": "a=\u501f\u8d37\u65b9\u5411\uff081\uff1a\u501f\uff0c-1\uff1a\u8d37\uff09;b=1;c=1;d=true"
        },
        "assist": {
          "type": "array",
          "items": {
            "$ref": "#/definitions/VoucherDetailReply.Assist"
          },
          "title": "a=\u671f\u95f4;b=8;c=[];d=true"
        }
      }
    },
    "VoucherDetailReply.SourceBill": {
      "type": "object",
      "properties": {
        "src_bill_id": {
          "type": "string",
          "title": "a=\u4e1a\u52a1\u5355\u636eid;b=999999999;c=111;"
        },
        "src_bill_type": {
          "type": "string",
          "title": "a=\u4e1a\u52a1\u5355\u636e\u7c7b\u578b\u8be6\u89c1[\u57fa\u7840\u8d44\u6599\u53ca\u5355\u636e\u7c7b\u578b](https://open.jdy.com/#/files/api/detail?index=3&categrayId=3cc8ee9a663e11eda5c84b5d383a2b93&id=dd7ee492712611eda0b375f5553347df);c=sal_order_bill"
        },
        "src_bill_no": {
          "type": "string",
          "title": "a=\u4e1a\u52a1\u5355\u636enumber;b=999999999;c=BM001;d=true"
        }
      }
    },
    "VoucherListReply": {
      "type": "object",
      "properties": {
        "total_page": {
          "type": "integer",
          "format": "int32",
          "title": "a=\u603b\u9875\u6570;b=1000;c=100;d=false"
        },
        "current_page_size": {
          "type": "integer",
          "format": "int32",
          "title": "a=\u5f53\u524d\u9875\u6761\u6570;b=100;c=1;d=false"
        },
        "count": {
          "type": "string",
          "title": "a=\u603b\u6761\u6570;b=999999;c=1;d=false"
        },
        "page_size": {
          "type": "integer",
          "format": "int32",
          "title": "a=\u6bcf\u9875\u6761\u6570;b=100;c=100;d=false"
        },
        "page": {
          "type": "integer",
          "format": "int32",
          "title": "a=\u5f53\u524d\u9875\u7801;b=1000;c=1;d=false"
        },
        "rows": {
          "type": "array",
          "items": {
            "$ref": "#/definitions/VoucherListReply.Row"
          },
          "title": "a=\u6570\u636e\u884c;b=999999;c=[];d=false"
        }
      }
    },
    "VoucherListReply.Row": {
      "type": "object",
      "properties": {
        "id": {
          "type": "string",
          "title": "a=\u51ed\u8bc1id;b=2147483647;c=1;d=true"
        },
        "date": {
          "type": "string",
          "title": "a=\u51ed\u8bc1\u65e5\u671f;b=10;c=2022-06-09;d=true"
        },
        "period": {
          "type": "string",
          "title": "a=\u51ed\u8bc1\u671f\u95f4;b=6;c=202206;d=true"
        },
        "number": {
          "type": "string",
          "title": "a=\u51ed\u8bc1\u53f7;b=100;c=1;d=true"
        },
        "voucher_no": {
          "type": "string",
          "title": "a=\u51ed\u8bc1\u5b57\u53f7;b=1;c=\u8bb0;d=true"
        },
        "bill_status": {
          "type": "string",
          "title": "a=\u72b6\u6001,\u6682\u5b58\uff1a\u201cA\u201d\uff0c\u4fdd\u5b58\uff1a\u201cB\u201d\uff0c\u5df2\u5ba1\u6838\uff1a\u201cC\u201d\uff0c\u5df2\u4f5c\u5e9f\uff1a\u201cD\u201d;b=1;c=A;d=true"
        },
        "group_id": {
          "type": "string",
          "title": "a=\u51ed\u8bc1\u5b57id;b=2147483647;c=1;d=true"
        },
        "group_number": {
          "type": "string",
          "title": "a=\u51ed\u8bc1\u5b57\u7f16\u7801;b=30;c=001;d=true"
        },
        "group_name": {
          "type": "string",
          "title": "a=\u51ed\u8bc1\u5b57\u540d\u79f0;b=30;c=\u8bb0;d=true"
        },
        "debit_total": {
          "type": "string",
          "title": "a=\u501f\u65b9\u603b\u91d1\u989d;b=2^128;c=100;d=true"
        },
        "credit_total": {
          "type": "string",
          "title": "a=\u8d37\u65b9\u603b\u91d1\u989d;b=2^128;c=100;d=true"
        },
        "source_bill_type": {
          "type": "string",
          "title": "\u8fc7\u65f6\u5b57\u6bb5\uff0c\u4e0d\u751f\u6210\u5bf9\u5916API\u6587\u6863:\u6a21\u7cca\u641c\u7d22"
        },
        "source_bill_id": {
          "type": "string",
          "title": "\u8fc7\u65f6\u5b57\u6bb5\uff0c\u4e0d\u751f\u6210\u5bf9\u5916API\u6587\u6863:\u6a21\u7cca\u641c\u7d22"
        },
        "have_reverse": {
          "type": "boolean",
          "title": "a=\u662f\u5426\u5df2\u88ab\u51b2\u9500;b=5;c=true;d=true"
        },
        "is_reverse": {
          "type": "boolean",
          "title": "a=\u662f\u5426\u51b2\u9500\u51ed\u8bc1;b=5;c=true;d=true"
        },
        "remark": {
          "type": "string",
          "title": "a=\u5907\u6ce8;b=100;c=\u5907\u6ce8;d=true"
        },
        "source_bill_no": {
          "type": "string",
          "title": "a=\u5916\u90e8\u552f\u4e00\u6807\u8bc6;b=30;c=001;d=false"
        },
        "src_bill": {
          "type": "array",
          "items": {
            "$ref": "#/definitions/Row.SourceBill"
          },
          "title": "a=\u51ed\u8bc1\u5173\u8054\u7684\u6e90\u5355\u4fe1\u606f;b=8;c=[];"
        }
      }
    },
    "VoucherSaveRequest": {
      "type": "object",
      "properties": {
        "items": {
          "type": "array",
          "items": {
            "$ref": "#/definitions/VoucherSaveRequest.Item"
          },
          "title": "a=\u51ed\u8bc1\u4fdd\u5b58\u5217\u8868;b=100;c=[];d=true"
        }
      }
    },
    "VoucherSaveRequest.Item": {
      "type": "object",
      "properties": {
        "id": {
          "type": "string",
          "title": "a=id\uff08\u4fee\u6539\u65f6\u5fc5\u586b\uff09;b=2147483647;c=1;d=false"
        },
        "date": {
          "type": "string",
          "title": "a=\u51ed\u8bc1\u65e5\u671f YYYY-MM-DD\u5f62\u5f0f;b=10;c=2022-07-13;d=true"
        },
        "group_id": {
          "type": "string",
          "title": "a=\u51ed\u8bc1\u5b57id\uff08\u51ed\u8bc1\u5b57id\u4e0e\u51ed\u8bc1\u5b57\u7f16\u7801\u4e8c\u9009\u4e00\uff09;b=2147483647;c=1;d=true"
        },
        "group_number": {
          "type": "string",
          "title": "a=\u4f20\u5165group_number\u65f6\uff0cid\u975e\u5fc5\u586b;b=30;c=001;d=true"
        },
        "number": {
          "type": "string",
          "title": "a=\u51ed\u8bc1\u53f7\uff0c\u672a\u586b\u5199\u65f6\u81ea\u52a8\u586b\u8865\u65ad\u53f7;b=30;c=001;d=false"
        },
        "remark": {
          "type": "string",
          "title": "a=\u5907\u6ce8;b=100;c=\u65e0;d=false"
        },
        "attachment_ids": {
          "type": "array",
          "items": {
            "type": "string"
          },
          "title": "a=\u5173\u8054\u51ed\u8bc1\u9644\u4ef6\uff08\u6765\u6e90\u4e8e\u51ed\u8bc1\u9644\u4ef6\u5217\u8868\u63a5\u53e3\uff0c\u8981\u6c42\u6240\u586b\u9644\u4ef6\u5fc5\u987b\u6709\u540c\u4e00\u4e2aadjustid\uff09;b=2147483647;c=[];d=false"
        },
        "entry_list": {
          "type": "array",
          "items": {
            "$ref": "#/definitions/Item.Entry"
          },
          "title": "a=\u5206\u5f55\u5217\u8868;b=100;c=[];d=true"
        },
        "source_bill_no": {
          "type": "string",
          "title": "a=\u5916\u90e8\u552f\u4e00\u6807\u8bc6\uff0c\u5df2\u5b58\u5728\u65f6\u4e0d\u5141\u8bb8\u4fdd\u5b58\u51ed\u8bc1;b=30;c=001;d=false"
        }
      }
    }
  }
}